README.rst
setup.py
nyt_pyiap.egg-info/PKG-INFO
nyt_pyiap.egg-info/SOURCES.txt
nyt_pyiap.egg-info/dependency_links.txt
nyt_pyiap.egg-info/requires.txt
nyt_pyiap.egg-info/top_level.txt
pyiap/__init__.py
pyiap/make_iap_request.py
pyiap/pyiap_django_middleware.py
pyiap/pyiap_flask_middleware.py
pyiap/utils.py