Metadata-Version: 1.1
Name: nyt-pyiap
Version: 0.1.9
Summary: Python utility functions and Django/Flask middlewares for validating JWT tokens from Google's Identity-Aware Proxy
Home-page: https://github.com/newsdev/nyt-pyiap
Author: Jeremy Bowers
Author-email: jeremy.bowers@nytimes.com
License: Apache License 2.0
Keywords: google identity-aware proxy iap jwt
Platform: UNKNOWN
Classifier: Development Status :: 3 - Alpha
Classifier: Intended Audience :: Developers
Classifier: Topic :: Software Development :: Libraries :: Python Modules
Classifier: Programming Language :: Python
Classifier: Programming Language :: Python :: 3
Classifier: Programming Language :: Python :: 3.6
